sdnotify_wrapper_py-1.0.0.dist-info/METADATA
sdnotify_wrapper_py-1.0.0.dist-info/WHEEL
sdnotify_wrapper_py-1.0.0.dist-info/entry_points.txt
sdnotify_wrapper_py-1.0.0.dist-info/LICENSE.txt
sdnotify_wrapper.py
sdnotify_wrapper_py-1.0.0.dist-info/RECORD
