Metadata-Version: 2.1
Name: sdnotify-wrapper-py
Version: 1.0.0
Summary: Notify readiness to systemd by writing to stdout in a service
Keywords: systemd daemon s6 sd_notify
Author-Email: Simon Holesch <simon@holesch.de>
License: MIT License
Classifier: Development Status :: 5 - Production/Stable
Classifier: Environment :: Console
Classifier: Intended Audience :: Developers
Classifier: License :: OSI Approved :: MIT License
Classifier: Operating System :: POSIX :: Linux
Classifier: Programming Language :: Python
Classifier: Programming Language :: Python :: 3.7
Classifier: Programming Language :: Python :: 3.8
Classifier: Programming Language :: Python :: 3.9
Classifier: Programming Language :: Python :: 3.10
Classifier: Programming Language :: Python :: 3.11
Classifier: Programming Language :: Python :: 3.12
Classifier: Programming Language :: Python :: 3.13
Classifier: Topic :: System :: Boot :: Init
Classifier: Topic :: System :: Systems Administration
Project-URL: Issues, https://github.com/holesch/sdnotify-wrapper-py/issues
Project-URL: Source, https://github.com/holesch/sdnotify-wrapper-py
Requires-Python: >=3.7
Provides-Extra: test
Requires-Dist: black; extra == "test"
Requires-Dist: codespell; extra == "test"
Requires-Dist: isort; extra == "test"
Requires-Dist: pylint; extra == "test"
